LICENSE
MANIFEST.in
README.md
setup.py
congas/Interface.py
congas/__init__.py
congas/utils.py
congas/data/example1_clust_ids.csv
congas/data/example1_cnv.csv
congas/data/example1_cnv_mat.csv
congas/data/example1_data.csv
congas/models/HmmMixtureRNA.py
congas/models/HmmSegmenter.py
congas/models/HmmSimple.py
congas/models/MixtureCategorical.py
congas/models/MixtureDirichlet.py
congas/models/MixtureGaussian.py
congas/models/MixtureGaussianDMP.py
congas/models/MixtureGaussianEXP.py
congas/models/MixtureGaussianGenes.py
congas/models/MixtureGaussianNorm.py
congas/models/MixtureGaussianOld.py
congas/models/Model.py
congas/models/__init__.py
congas_OLD.egg-info/PKG-INFO
congas_OLD.egg-info/SOURCES.txt
congas_OLD.egg-info/dependency_links.txt
congas_OLD.egg-info/not-zip-safe
congas_OLD.egg-info/requires.txt
congas_OLD.egg-info/top_level.txt
congas_old.egg-info/PKG-INFO
congas_old.egg-info/SOURCES.txt
congas_old.egg-info/dependency_links.txt
congas_old.egg-info/not-zip-safe
congas_old.egg-info/requires.txt
congas_old.egg-info/top_level.txt
docs/anneal.html