Metadata-Version: 2.1
Name: congas-old
Version: 0.0.3
Summary: Copy Number genotyping from single cell RNA sequencing
Home-page: https://github.com/Militeee/congas
Author: Salvatore Milite
Author-email: militesalvatore@gmail.com
License: GPL-3.0
Keywords: scRNA scDNA RNA CNV CNA Cancer Copy-number Bioinformatics
Platform: UNKNOWN
Classifier: Development Status :: 3 - Alpha
Classifier: License :: OSI Approved :: GNU General Public License v3 (GPLv3)
Classifier: Programming Language :: Python :: 3.7
Classifier: Topic :: Scientific/Engineering :: Bio-Informatics
License-File: LICENSE
